verilog mini-projects/4_by_1_mux/mux.v
module mux(a, b, s, c, d, y);
    input [1:0] a, b, c, d, s;
    output reg [1:0] y; // it needs to be reg because y would be inside an always block

    always @(*) begin
        case (s)
            2'b00 : begin y <= a; end
            2'b01 : begin y <= b; end
            2'b10 : begin y <= c; end
            2'b11 : begin y <= d; end
            default : begin y <= 2'b00; end // if none match
        endcase
    end
endmodule

verilog mini-projects/4_by_1_mux/testbench.v
module tb();
    // Inputs
    reg [1:0] a, b, c, d, s;
    // Output
    wire [1:0] y;
    
    // Instantiate the mux
    mux dut(
        .a(a),
        .b(b),
        .c(c),
        .d(d),
        .s(s),
        .y(y)
    );

    // For waveform generation
    initial begin
        $dumpfile("dump.vcd");
        $dumpvars(0);
    end

    // Test stimulus
    initial begin
         // Initialize inputs
        a = 2'b00; b = 2'b01; c = 2'b10; d = 2'b11;
        #10;
        // Test case 1: select a (s = 00)
        s = 2'b00;
        #10;
        
        // Test case 2: select b (s = 01)
        s = 2'b01;
        #10;
        
        // Test case 3: select c (s = 10)
        s = 2'b10;
        #10;
        
        // Test case 4: select d (s = 11)
        s = 2'b11;
        #10;
        
        // Change input values and repeat tests
        a = 2'b11; b = 2'b10; c = 2'b01; d = 2'b00;
    
        // Test case 5: select a (s = 00)
        s = 2'b00;
        #10;
        
        // Test case 6: select b (s = 01)
        s = 2'b01;
        #10;
        
        // Test case 7: select c (s = 10)
        s = 2'b10;
        #10;
        
        // Test case 8: select d (s = 11)
        s = 2'b11;
        #10;

        $finish;
    end
endmodule

verilog mini-projects/4_by_1_mux/dump.vcd
$date
	Tue Dec 17 15:07:57 2024
$end
$version
	Icarus Verilog
$end
$timescale
	1s
$end
$scope module tb $end
$var wire 2 ! y [1:0] $end
$var reg 2 " a [1:0] $end
$var reg 2 # b [1:0] $end
$var reg 2 $ c [1:0] $end
$var reg 2 % d [1:0] $end
$var reg 2 & s [1:0] $end
$scope module dut $end
$var wire 2 ' a [1:0] $end
$var wire 2 ( b [1:0] $end
$var wire 2 ) c [1:0] $end
$var wire 2 * d [1:0] $end
$var wire 2 + s [1:0] $end
$var reg 2 , y [1:0] $end
$upscope $end
$upscope $end
$enddefinitions $end
$comment Show the parameter values. $end
$dumpall
$end
#0
$dumpvars
b0 ,
bx +
b11 *
b10 )
b1 (
b0 '
bx &
b11 %
b10 $
b1 #
b0 "
b0 !
$end
#10
b0 &
b0 +
#20
b1 !
b1 ,
b1 &
b1 +
#30
b10 !
b10 ,
b10 &
b10 +
#40
b11 !
b11 ,
b11 &
b11 +
#50
b0 &
b0 +
b0 %
b0 *
b1 $
b1 )
b10 #
b10 (
b11 "
b11 '
#60
b10 !
b10 ,
b1 &
b1 +
#70
b1 !
b1 ,
b10 &
b10 +
#80
b0 !
b0 ,
b11 &
b11 +
