d-flip-flops/design.v
module dflop(reset, clk, D, Q);
    input reset, clk, D;
    output reg Q; 
    // since Q is a sort of memory (the value of 1 may not change even if inputs change)
    // it is a sort of register (reg)

    // always block is a procedral block (like initial)
    // however initial is best suited for testbenches
    //always = design + testbench

    // always @(sensitivity list)(will keep running until there is a value change)

    always @(posedge clk) begin
        if (reset == 1'b1) begin
            Q <= 1'b0;
        end

        else begin
            Q <= D;
        end
    end

endmodule

verilog mini-projects/d-flip-flops/testbench.v
module tb();
    reg reset, clk, D;
    wire Q;
    dflop dut(
        .reset(reset), 
        .clk(clk), 
        .D(D), 
        .Q(Q)
    );

    // Generate a clock and no sensitivity in testbench
    always begin
        clk <= 1'b0;
        #50; // always half of input, because one full clock goes up and down
        clk <= 1'b1;
        #50;
    end

    initial begin
        reset <= 1'b1;
        #100;

        reset <= 1'b0;
        #100;

        D <= 1'b1;
        #100;

        D<= 1'b0;
        #100;
        // since i put an always begin, it will run indefinately, so i need finish
        $finish;
    end

    initial begin
        $dumpfile("dump.vcd");
        $dumpvars(0);
    end
endmodule

verilog mini-projects/d-flip-flops/dump.vcd
$date
	Sun Dec 15 17:41:53 2024
$end
$version
	Icarus Verilog
$end
$timescale
	1s
$end
$scope module tb $end
$var wire 1 ! Q $end
$var reg 1 " D $end
$var reg 1 # clk $end
$var reg 1 $ reset $end
$scope module dut $end
$var wire 1 " D $end
$var wire 1 # clk $end
$var wire 1 $ reset $end
$var reg 1 ! Q $end
$upscope $end
$upscope $end
$enddefinitions $end
$comment Show the parameter values. $end
$dumpall
$end
#0
$dumpvars
1$
0#
x"
x!
$end
#50
0!
1#
#100
0#
0$
#150
x!
1#
#200
0#
1"
#250
1!
1#
#300
0#
0"
#350
0!
1#
